<?xml version = '1.0' encoding = 'UTF-8'?>
<Relation class="oracle.dbtools.crest.model.design.logical.Relation" name="FK_TEL_CLIENTE_TELEFONE" directorySegmentName="seg_0" id="7BB9BD25-C669-DD16-1052-56DC084F855A">
<createdBy>prisc</createdBy>
<createdTime>2022-05-18 20:54:02 UTC</createdTime>
<generatorID>D857EE44-16C6-1767-69F9-2ECD7823DAF0</generatorID>
<ownerDesignName>Prikka_Restaurante2</ownerDesignName>
<engineerTo>
<item key="E72E33A6-2E1D-FEF1-9264-2FE688EECA92" value="true"/>
</engineerTo>
<sourcePk>2D44DB95-C15B-3028-EEA0-AA996B62111D</sourcePk>
<identifying>true</identifying>
<optionalSource>true</optionalSource>
<optionalTarget>false</optionalTarget>
<sourceCardinality>1</sourceCardinality>
<sourceEntity>9277E849-FD90-11A1-CF8F-F03B46A7825C</sourceEntity>
<targetCardinalityString>*</targetCardinalityString>
<targetEntity>8FCD98B4-2901-C1CB-EA74-C2600D89F909</targetEntity>
<transferable>true</transferable>
<deleteRule>NO ACTION</deleteRule>
</Relation>